georesolver/__init__.py
georesolver/base.py
georesolver/resolver.py
georesolver/data/mappings/places_map.json
georesolver/utils/LoggerHandler.py
georesolver-0.2.2.dist-info/licenses/LICENSE
georesolver-0.2.2.dist-info/METADATA
georesolver-0.2.2.dist-info/WHEEL
georesolver-0.2.2.dist-info/top_level.txt
georesolver-0.2.2.dist-info/RECORD
