Metadata-Version: 2.4
Name: georesolver
Version: 0.2.2
Summary: Multi-source place name to coordinates resolver using TGN, WHG, GeoNames, and Wikidata
Author-email: Jairo Antonio Melo Florez <jairoantoniomelo@gmail.com>
License: GPL-3.0-only
Project-URL: Homepage, https://github.com/jairomelo/Georesolver
Project-URL: Issues, https://github.com/jairomelo/Georesolver/issues
Project-URL: Documentation, https://jairomelo.com/Georesolver/
Keywords: geocoding,georesolver,geonames,wikidata,tgn,whg
Classifier: Development Status :: 4 - Beta
Classifier: Intended Audience :: Developers
Classifier: License :: OSI Approved :: MIT License
Classifier: Natural Language :: English
Classifier: Programming Language :: Python :: 3
Classifier: Programming Language :: Python :: 3.9
Classifier: Programming Language :: Python :: 3.10
Classifier: Programming Language :: Python :: 3.11
Classifier: Programming Language :: Python :: 3.12
Classifier: Programming Language :: Python :: 3.13
Classifier: Topic :: Software Development :: Libraries :: Python Modules
Classifier: Topic :: Scientific/Engineering :: Information Analysis
Classifier: Topic :: Scientific/Engineering :: GIS
Classifier: Topic :: Utilities
Requires-Python: >=3.9
License-File: LICENSE
Requires-Dist: SPARQLWrapper~=2.0.0
Requires-Dist: RapidFuzz~=3.13.0
Requires-Dist: requests~=2.32.4
Requires-Dist: python-dotenv~=1.1.0
Requires-Dist: ratelimit~=2.2.1
Requires-Dist: requests-cache~=1.2.1
Requires-Dist: tqdm~=4.67.1
Requires-Dist: pandas~=2.3.0
Requires-Dist: pycountry~=24.6.1
Provides-Extra: dev
Requires-Dist: pytest>=8.0.0; extra == "dev"
Requires-Dist: pytest-cov; extra == "dev"
Requires-Dist: mypy; extra == "dev"
Requires-Dist: ruff; extra == "dev"
Dynamic: license-file
